[{"id":"4","parent_id":null,"name":"Ti\u1ebft ki\u1ec7m","description":"<p>Ti\u1ebft ki\u1ec7m<\/p>","weight":null,"status":"2","user_id":null,"created":"2015-09-17 06:29:29","modified":"2015-09-17 06:29:53"},{"id":"3","parent_id":null,"name":"M\u1edbi v\u1ec1","description":"<p>M\u1edbi v\u1ec1<\/p>","weight":null,"status":"2","user_id":null,"created":"2015-09-17 06:23:03","modified":"2015-09-17 06:23:03"},{"id":"2","parent_id":null,"name":"Khuy\u1ebfn m\u00e3i","description":"<p>Khuy\u1ebfn m&atilde;i<\/p>","weight":null,"status":"2","user_id":null,"created":"2015-09-17 06:16:03","modified":"2015-09-17 06:16:03"},{"id":"1","parent_id":null,"name":"B\u00e1n ch\u1ea1y","description":"<p>B&aacute;n ch\u1ea1y<\/p>","weight":null,"status":"2","user_id":null,"created":"2015-09-13 19:28:19","modified":"2015-09-17 06:13:24"}]